jssh/__init__.py
jssh/gl.py
jssh/jssh.py
jssh/progressbar.py
jssh/server.py
jssh-4.0.8.dist-info/LICENSE
jssh-4.0.8.dist-info/METADATA
jssh-4.0.8.dist-info/WHEEL
jssh-4.0.8.dist-info/entry_points.txt
jssh-4.0.8.dist-info/top_level.txt
jssh-4.0.8.dist-info/RECORD
