Metadata-Version: 2.1
Name: jssh
Version: 4.0.8
Summary: GUI,ssh to multiple servers
Home-page: https://github.com/fnhchaiyin/jssh
Author: jhy
Author-email: fnhchaiying@163.com
License: UNKNOWN
Platform: UNKNOWN
Classifier: Programming Language :: Python :: 2.7
Classifier: License :: OSI Approved :: MIT License
Classifier: Operating System :: OS Independent
Requires-Dist: paramiko
